MANIFEST.in
README.rst
primme.c
primme.pyx
pyproject.toml
setup.py
primme.egg-info/PKG-INFO
primme.egg-info/SOURCES.txt
primme.egg-info/dependency_links.txt
primme.egg-info/requires.txt
primme.egg-info/top_level.txt
src/primme/eigs/auxiliary_eigs.c
src/primme/eigs/auxiliary_eigs.h
src/primme/eigs/auxiliary_eigs_normal.c
src/primme/eigs/auxiliary_eigs_normal.h
src/primme/eigs/common_eigs.h
src/primme/eigs/convergence.c
src/primme/eigs/convergence.h
src/primme/eigs/correction.c
src/primme/eigs/correction.h
src/primme/eigs/factorize.c
src/primme/eigs/factorize.h
src/primme/eigs/init.c
src/primme/eigs/init.h
src/primme/eigs/inner_solve.c
src/primme/eigs/inner_solve.h
src/primme/eigs/main_iter.c
src/primme/eigs/main_iter.h
src/primme/eigs/ortho.c
src/primme/eigs/ortho.h
src/primme/eigs/primme_c.c
src/primme/eigs/primme_c.h
src/primme/eigs/primme_f77.c
src/primme/eigs/primme_interface.c
src/primme/eigs/restart.c
src/primme/eigs/restart.h
src/primme/eigs/solve_projection.c
src/primme/eigs/solve_projection.h
src/primme/eigs/template_normal.h
src/primme/eigs/update_W.c
src/primme/eigs/update_W.h
src/primme/eigs/update_projection.c
src/primme/eigs/update_projection.h
src/primme/include/auxiliary.h
src/primme/include/blaslapack.h
src/primme/include/common.h
src/primme/include/cublas_wrapper.h
src/primme/include/magma_wrapper.h
src/primme/include/memman.h
src/primme/include/notemplate.h
src/primme/include/numerical.h
src/primme/include/primme.h
src/primme/include/primme_eigs.h
src/primme/include/primme_eigs_f77.h
src/primme/include/primme_f77.h
src/primme/include/primme_interface.h
src/primme/include/primme_svds.h
src/primme/include/primme_svds_f77.h
src/primme/include/template.h
src/primme/include/template_types.h
src/primme/include/template_undef.h
src/primme/include/wtime.h
src/primme/linalg/auxiliary.c
src/primme/linalg/blaslapack.c
src/primme/linalg/blaslapack_private.h
src/primme/linalg/cublas_wrapper.c
src/primme/linalg/magma_wrapper.c
src/primme/linalg/memman.c
src/primme/linalg/wtime.c
src/primme/svds/primme_svds_c.c
src/primme/svds/primme_svds_c.h
src/primme/svds/primme_svds_f77.c
