Metadata-Version: 2.1
Name: primme
Version: 3.2.2
Summary: PRIMME wrapper for Python
Author: Lingfei Wu
Author-email: Eloy Romero Alcalde <eromero@jlab.org>, Andreas Stathopoulos <andreas@cs.wm.edu>
Maintainer-email: Eloy Romero Alcalde <eromero@jlab.org>, Andreas Stathopoulos <andreas@cs.wm.edu>
License: BSD License
Project-URL: Homepage, https://www.cs.wm.edu/~andreas/software
Project-URL: Repository, https://github.com/primme/primme
Project-URL: Documentation, https://www.cs.wm.edu/~andreas/software/doc/readme.html
Project-URL: Issues, https://github.com/primme/primme/issues
Classifier: Development Status :: 5 - Production/Stable
Classifier: Programming Language :: Python :: 3
Classifier: Programming Language :: C
Classifier: License :: OSI Approved :: BSD License
Classifier: Intended Audience :: Science/Research
Classifier: Topic :: Scientific/Engineering
Classifier: Operating System :: Microsoft :: Windows
Classifier: Operating System :: POSIX
Classifier: Operating System :: Unix
Classifier: Operating System :: MacOS
Requires-Python: >=3.8
Requires-Dist: numpy
Requires-Dist: scipy
